pyliveupdate/__init__.py
pyliveupdate/config.py
pyliveupdate/instrumentation.py
pyliveupdate/ipc.py
pyliveupdate/register.py
pyliveupdate/startcontroller.py
pyliveupdate/startserver.py
pyliveupdate/update.py
pyliveupdate/client/__init__.py
pyliveupdate/client/client.py
pyliveupdate/client/logclient.py
pyliveupdate/controller/__init__.py
pyliveupdate/controller/logserver.py
pyliveupdate/controller/startcontroller.py
pyliveupdate/controller/updatecontroller-Copy1.py
pyliveupdate/controller/updatecontroller.py
pyliveupdate/grpc/__init__.py
pyliveupdate/grpc/codegen.py
pyliveupdate/grpc/updateregister_pb2.py
pyliveupdate/grpc/updateregister_pb2_grpc.py
pyliveupdate/grpc/updatestub_pb2.py
pyliveupdate/grpc/updatestub_pb2_grpc.py
pyliveupdate/grpc/updatestubproxy_pb2.py
pyliveupdate/grpc/updatestubproxy_pb2_grpc.py
pyliveupdate/server/__init__.py
pyliveupdate/server/logserver.py
pyliveupdate/server/server.py
pyliveupdate/stub/__init__.py
pyliveupdate/stub/logclient.py
pyliveupdate/stub/updatestub.py
pyliveupdate/stub/updatestubproxy.py
pyliveupdate/update/__init__.py
pyliveupdate/update/instrument.py
pyliveupdate/update/instrumenter.py
pyliveupdate/update/redefine.py
pyliveupdate/update/targetfinder.py
pyliveupdate/update/update.py
pyliveupdate/util/__init__.py
pyliveupdate/util/lib.py
pyliveupdate/util/prefixtree.py
pyliveupdate/util/render.py
pyliveupdate/util/update_old.py
pyliveupdate-0.3.1.data/scripts/flamegraph.pl
pyliveupdatescripts/__init__.py
pyliveupdatescripts/funcdebugger.py
pyliveupdatescripts/funcprofiler.py
pyliveupdatescripts/linedebugger.py
pyliveupdatescripts/lineprofiler.py
pyliveupdatescripts/processfunclogs.py
pyliveupdatescripts/updatebase.py
pyliveupdatescripts/vardebugger.py
pyliveupdate-0.3.1.dist-info/LICENSE
pyliveupdate-0.3.1.dist-info/METADATA
pyliveupdate-0.3.1.dist-info/WHEEL
pyliveupdate-0.3.1.dist-info/entry_points.txt
pyliveupdate-0.3.1.dist-info/top_level.txt
pyliveupdate-0.3.1.dist-info/RECORD
