Metadata-Version: 2.1
Name: pyliveupdate
Version: 0.3.1
Summary: A tool to manipulate python code at runtime for logging, profiling, debugging, etc.
Home-page: https://github.com/devopspp/pyliveupdate
Author: devopspp
License: GPLv3
Keywords: runtime instrumentation logging profiling debugging
Platform: UNKNOWN
Classifier: Development Status :: 3 - Alpha
Classifier: Environment :: Console
Classifier: Intended Audience :: Developers
Classifier: Intended Audience :: System Administrators
Classifier: License :: OSI Approved :: GNU General Public License (GPL)
Classifier: Topic :: System :: Logging
Classifier: Topic :: System :: Monitoring
Classifier: Topic :: Software Development :: Libraries :: Python Modules
Classifier: Topic :: Software Development :: Debuggers
Classifier: Programming Language :: Python :: 3
Requires-Python: >=3.5
Requires-Dist: bytecode
Requires-Dist: Werkzeug
Requires-Dist: grpcio
Requires-Dist: grpcio-tools
Requires-Dist: aenum
